Workbook

Sheet LEIA-ME
A1: Sistema comercial, onboarding e ROI
A2: Modelo para Excel ou importação no Google Sheets. Edite células amarelas com texto azul; fórmulas ficam em preto.
A4: Etapa | B4: Área | C4: Como usar
A5: 1 | B5: Pré-venda | C5: Use Roteiro Pré-venda durante a ligação e registre uma linha em Oportunidades.
A6: 2 | B6: Decisão de fit | C6: A planilha calcula nota, classificação e exposição financeira preliminar.
A7: 3 | B7: Escopo e preço | C7: Preencha Escopo Setup para estimar horas, custo, preço mínimo, preço sugerido e prazo.
A8: 4 | B8: Fechamento | C8: Ao ganhar, aprofunde o briefing na aba Onboarding; não pergunte novamente o que já foi coletado.
A9: 5 | B9: Plano do cliente | C9: Registre um agente por linha em Plano do Cliente, com função, limites, integrações e métricas.
A10: 6 | B10: Operação mensal | C10: Estime horas, tokens, custo e mensalidade em Operação Mensal.
A11: 7 | B11: Prova de valor | C11: Preencha Relatório ROI mensalmente com linha de base e resultados observados.

Sheet Parâmetros
A1: Parâmetros comerciais e operacionais
A2: Valores de exemplo. Substitua pelos custos, preços e capacidade reais da Avraham.
A4: Parâmetro | B4: Valor | C4: Observação
A5: Custo interno carregado por hora (R$) | B5: 120 | C5: Inclua salário/pró-labore, encargos, ferramentas e ociosidade.
A6: Valor comercial por hora (R$) | B6: 300 | C6: Referência para preço sugerido de setup.
A7: Margem bruta alvo | B7: 0.6 | C7: Usada para calcular preço mínimo saudável.
A8: Gestão do projeto sobre horas | B8: 0.15 | C8: Percentual adicional para coordenação.
A9: Contingência sobre horas | B9: 0.1 | C9: Reserva para risco e variação de escopo.
A10: Capacidade semanal por projeto (h) | B10: 20 | C10: Capacidade efetiva, não jornada total.
A11: Captura de valor mensal | B11: 0.1 | C11: Parcela do impacto conservador usada como referência de preço.
A12: Margem sobre tokens/infra | B12: 0.3 | C12: Markup operacional sobre custos variáveis.
A13: Câmbio USD/BRL | B13: 5.5 | C13: Exemplo; atualizar conforme política financeira.
A14: Modelo - entrada (USD/1M tokens) | B14: 1 | C14: Exemplo; substituir pelo modelo contratado.
A15: Modelo - saída (USD/1M tokens) | B15: 4 | C15: Exemplo; substituir pelo modelo contratado.
A16: Descoberta e diagnóstico (h) | B16: 4 | C16: Base por cliente.
... A26: Treinamento/handoff (h) | B26: 3 | C26: Por sessão.

Sheet Roteiro Pré-venda
A1: Roteiro da ligação de descoberta
A2: Perguntas para descobrir fit, impacto, escopo provável e argumentos da proposta.
A4: Bloco | B4: Pergunta | C4: O que revela | D4: Formato da resposta
A5: Contexto | B5: O que a empresa vende, para quem e por qual canal? | C5: Contexto comercial | D5: Texto
A6: Contexto | B6: Qual processo vocês gostariam de melhorar com IA? | C6: Caso de uso | D6: Texto
A7: Prioridade | B7: Por que isso virou prioridade agora? | C7: Urgência | D7: Texto
A8: Prioridade | B8: O que acontece se nada mudar nos próximos seis meses? | C8: Custo de inação | D8: Texto
A9: Dor | B9: Onde o processo mais trava, atrasa ou perde qualidade? | C9: Dor principal | D9: Texto
A10: Dor | B10: Conte um caso recente em que isso custou tempo, venda ou satisfação. | C10: Evidência | D10: Texto
A11: Volume | B11: Quantos contatos ou solicitações entram por mês? | C11: Escala | D11: Número
A12: Impacto | B12: Qual é o ticket médio e a conversão atual? | C12: Receita exposta | D12: Moeda + %
A13: Impacto | B13: Quantos contatos ficam sem resposta ou sem follow-up? | C13: Abandono | D13: % ou número
A14: Impacto | B14: Quanto tempo leva a primeira resposta? | C14: Velocidade | D14: Minutos
A15: Impacto | B15: Quantas pessoas e horas mensais são gastas nesse processo? | C15: Custo de trabalho | D15: Número
... A26: Métrica | B26: O cliente aceita medir uma linha de base antes do go-live? | C26: Mensurabilidade | D26: Sim/Não

Sheet Oportunidades
A1: Registro e qualificação de oportunidades
A2: Uma linha por oportunidade. Notas de 0 a 5; bloqueador crítico força a classificação Sem fit.
A4: ID | B4: Data | C4: Cliente | D4: Vendedor | E4: Segmento | F4: Contatos/mês | G4: Ticket médio (R$) | H4: Conversão atual | I4: % sem follow-up | J4: 1ª resposta (min) | K4: Dor e prioridade (0-5) | L4: Impacto econômico (0-5) | M4: Volume/repetição (0-5) | N4: Prontidão operacional (0-5) | O4: Fit comercial (0-5) | P4: Bloqueador crítico? | Q4: Nota de fit | R4: Classificação | S4: Receita exposta/mês | T4: Dor principal | U4: Resultado desejado | V4: Processo atual | W4: Sistemas/canais | X4: Decisor/dono | Y4: Faixa de investimento | Z4: Urgência/data | AA4: Próximo passo | AB4: Status | AC4: Tese para proposta | AD4: Motivo sem fit/perda
A5: OP-001 | B5: 05/10/2026 | C5: Cliente Exemplo | D5: Closer | E5: Serviços | F5: 1200 | G5: 2500 | H5: 0.08 | I5: 0.28 | J5: 180 | K5: 5 | L5: 4 | M5: 5 | N5: 3 | O5: 4 | P5: Não | Q5: =K5*6+L5*5+M5*3+N5*3+O5*3 -> 86 | R5: =IF(P5="Sim","Sem fit",IF(Q5>=75,"Fit forte",IF(Q5>=55,"Fit condicionado","Sem fit"))) -> Fit forte | S5: =F5*I5*H5*G5 -> 67200 | T5: Leads sem continuidade | U5: Proteger e qualificar 24/7 | V5: Atendimento manual sem cadência | W5: WhatsApp + CRM | X5: Diretor comercial | Y5: R$ 8 mil a R$ 15 mil | Z5: 30 dias | AA5: Agendar proposta | AB5: Fit forte | AC5: Proteger resposta, qualificação e follow-up antes de ampliar.
Q6: =IF(C6="","",K6*6+L6*5+M6*3+N6*3+O6*3) | R6: =IF(C6="","",IF(P6="Sim","Sem fit",IF(Q6>=75,"Fit forte",IF(Q6>=55,"Fit condicionado","Sem fit")))) | S6: =IF(C6="","",F6*I6*H6*G6)
Q7: =IF(C7="","",K7*6+L7*5+M7*3+N7*3+O7*3) | R7: =IF(C7="","",IF(P7="Sim","Sem fit",IF(Q7>=75,"Fit forte",IF(Q7>=55,"Fit condicionado","Sem fit")))) | S7: =IF(C7="","",F7*I7*H7*G7)
Q8: =IF(C8="","",K8*6+L8*5+M8*3+N8*3+O8*3) | R8: =IF(C8="","",IF(P8="Sim","Sem fit",IF(Q8>=75,"Fit forte",IF(Q8>=55,"Fit condicionado","Sem fit")))) | S8: =IF(C8="","",F8*I8*H8*G8)
Q9: =IF(C9="","",K9*6+L9*5+M9*3+N9*3+O9*3) | R9: =IF(C9="","",IF(P9="Sim","Sem fit",IF(Q9>=75,"Fit forte",IF(Q9>=55,"Fit condicionado","Sem fit")))) | S9: =IF(C9="","",F9*I9*H9*G9)
Q10: =IF(C10="","",K10*6+L10*5+M10*3+N10*3+O10*3) | R10: =IF(C10="","",IF(P10="Sim","Sem fit",IF(Q10>=75,"Fit forte",IF(Q10>=55,"Fit condicionado","Sem fit")))) | S10: =IF(C10="","",F10*I10*H10*G10)
Q11: =IF(C11="","",K11*6+L11*5+M11*3+N11*3+O11*3) | R11: =IF(C11="","",IF(P11="Sim","Sem fit",IF(Q11>=75,"Fit forte",IF(Q11>=55,"Fit condicionado","Sem fit")))) | S11: =IF(C11="","",F11*I11*H11*G11)
Q12: =IF(C12="","",K12*6+L12*5+M12*3+N12*3+O12*3) | R12: =IF(C12="","",IF(P12="Sim","Sem fit",IF(Q12>=75,"Fit forte",IF(Q12>=55,"Fit condicionado","Sem fit")))) | S12: =IF(C12="","",F12*I12*H12*G12)
Q13: =IF(C13="","",K13*6+L13*5+M13*3+N13*3+O13*3) | R13: =IF(C13="","",IF(P13="Sim","Sem fit",IF(Q13>=75,"Fit forte",IF(Q13>=55,"Fit condicionado","Sem fit")))) | S13: =IF(C13="","",F13*I13*H13*G13)
Q14: =IF(C14="","",K14*6+L14*5+M14*3+N14*3+O14*3) | R14: =IF(C14="","",IF(P14="Sim","Sem fit",IF(Q14>=75,"Fit forte",IF(Q14>=55,"Fit condicionado","Sem fit")))) | S14: =IF(C14="","",F14*I14*H14*G14)
Q15: =IF(C15="","",K15*6+L15*5+M15*3+N15*3+O15*3) | R15: =IF(C15="","",IF(P15="Sim","Sem fit",IF(Q15>=75,"Fit forte",IF(Q15>=55,"Fit condicionado","Sem fit")))) | S15: =IF(C15="","",F15*I15*H15*G15)
Q16: =IF(C16="","",K16*6+L16*5+M16*3+N16*3+O16*3) | R16: =IF(C16="","",IF(P16="Sim","Sem fit",IF(Q16>=75,"Fit forte",IF(Q16>=55,"Fit condicionado","Sem fit")))) | S16: =IF(C16="","",F16*I16*H16*G16)
Q17: =IF(C17="","",K17*6+L17*5+M17*3+N17*3+O17*3) | R17: =IF(C17="","",IF(P17="Sim","Sem fit",IF(Q17>=75,"Fit forte",IF(Q17>=55,"Fit condicionado","Sem fit")))) | S17: =IF(C17="","",F17*I17*H17*G17)
... Q105: =IF(C105="","",K105*6+L105*5+M105*3+N105*3+O105*3) | R105: =IF(C105="","",IF(P105="Sim","Sem fit",IF(Q105>=75,"Fit forte",IF(Q105>=55,"Fit condicionado","Sem fit")))) | S105: =IF(C105="","",F105*I105*H105*G105)

Sheet Escopo Setup
A1: Estimativa de setup
A2: Quantifique o escopo. O preço mínimo protege margem; o sugerido usa a maior referência entre custo e hora comercial.
A4: ID oportunidade | B4: Cliente | C4: Complexidade | D4: Agentes | E4: Fluxos | F4: Fontes conhecimento | G4: Integrações simples | H4: Integrações complexas | I4: Canais | J4: Ações customizadas | K4: Cenários teste | L4: Sessões treinamento | M4: Horas migração/outros | N4: Descoberta (h) | O4: Mapeamento (h) | P4: Agentes (h) | Q4: Fluxos (h) | R4: Conhecimento (h) | S4: Integrações (h) | T4: Canais (h) | U4: Customização (h) | V4: Testes (h) | W4: Treinamento (h) | X4: Subtotal (h) | Y4: Gestão (h) | Z4: Contingência (h) | AA4: Total (h) | AB4: Custo interno | AC4: Preço mínimo | AD4: Preço sugerido | AE4: Margem sugerida | AF4: Prazo (semanas)
A5: OP-001 | B5: Cliente Exemplo | C5: 1 | D5: 1 | E5: 6 | F5: 8 | G5: 1 | H5: 0 | I5: 1 | J5: 1 | K5: 12 | L5: 1 | M5: 0 | N5: =IF(B5="","",Parâmetros!$B$16*C5) -> 4 | O5: =IF(B5="","",Parâmetros!$B$17*C5) -> 6 | P5: =IF(B5="","",D5*Parâmetros!$B$18*C5) -> 10 | Q5: =IF(B5="","",E5*Parâmetros!$B$19*C5) -> 9 | R5: =IF(B5="","",F5*Parâmetros!$B$20*C5) -> 4 | S5: =IF(B5="","",(G5*Parâmetros!$B$21+H5*Parâmetros!$B$22)*C5) -> 8 | T5: =IF(B5="","",I5*Parâmetros!$B$23*C5) -> 4 | U5: =IF(B5="","",J5*Parâmetros!$B$24*C5) -> 6 | V5: =IF(B5="","",K5*Parâmetros!$B$25*C5) -> 6 | W5: =IF(B5="","",L5*Parâmetros!$B$26*C5) -> 3 | X5: =IF(B5="","",SUM(N5:W5)+M5) -> 60 | Y5: =IF(B5="","",X5*Parâmetros!$B$8) -> 9 | Z5: =IF(B5="","",X5*Parâmetros!$B$9) -> 6 | AA5: =IF(B5="","",SUM(X5:Z5)) -> 75 | AB5: =IF(B5="","",AA5*Parâmetros!$B$5) -> 9000 | AC5: =IF(B5="","",AB5/(1-Parâmetros!$B$7)) -> 22500 | AD5: =IF(B5="","",MAX(AA5*Parâmetros!$B$6,AC5)) -> 22500 | AE5: =IF(B5="","",(AD5-AB5)/AD5) -> 0.6 | AF5: =IF(B5="","",AA5/Parâmetros!$B$10) -> 3.75
N6: =IF(B6="","",Parâmetros!$B$16*C6) | O6: =IF(B6="","",Parâmetros!$B$17*C6) | P6: =IF(B6="","",D6*Parâmetros!$B$18*C6) | Q6: =IF(B6="","",E6*Parâmetros!$B$19*C6) | R6: =IF(B6="","",F6*Parâmetros!$B$20*C6) | S6: =IF(B6="","",(G6*Parâmetros!$B$21+H6*Parâmetros!$B$22)*C6) | T6: =IF(B6="","",I6*Parâmetros!$B$23*C6) | U6: =IF(B6="","",J6*Parâmetros!$B$24*C6) | V6: =IF(B6="","",K6*Parâmetros!$B$25*C6) | W6: =IF(B6="","",L6*Parâmetros!$B$26*C6) | X6: =IF(B6="","",SUM(N6:W6)+M6) | Y6: =IF(B6="","",X6*Parâmetros!$B$8) | Z6: =IF(B6="","",X6*Parâmetros!$B$9) | AA6: =IF(B6="","",SUM(X6:Z6)) | AB6: =IF(B6="","",AA6*Parâmetros!$B$5) | AC6: =IF(B6="","",AB6/(1-Parâmetros!$B$7)) | AD6: =IF(B6="","",MAX(AA6*Parâmetros!$B$6,AC6)) | AE6: =IF(B6="","",(AD6-AB6)/AD6) | AF6: =IF(B6="","",AA6/Parâmetros!$B$10)
N7: =IF(B7="","",Parâmetros!$B$16*C7) | O7: =IF(B7="","",Parâmetros!$B$17*C7) | P7: =IF(B7="","",D7*Parâmetros!$B$18*C7) | Q7: =IF(B7="","",E7*Parâmetros!$B$19*C7) | R7: =IF(B7="","",F7*Parâmetros!$B$20*C7) | S7: =IF(B7="","",(G7*Parâmetros!$B$21+H7*Parâmetros!$B$22)*C7) | T7: =IF(B7="","",I7*Parâmetros!$B$23*C7) | U7: =IF(B7="","",J7*Parâmetros!$B$24*C7) | V7: =IF(B7="","",K7*Parâmetros!$B$25*C7) | W7: =IF(B7="","",L7*Parâmetros!$B$26*C7) | X7: =IF(B7="","",SUM(N7:W7)+M7) | Y7: =IF(B7="","",X7*Parâmetros!$B$8) | Z7: =IF(B7="","",X7*Parâmetros!$B$9) | AA7: =IF(B7="","",SUM(X7:Z7)) | AB7: =IF(B7="","",AA7*Parâmetros!$B$5) | AC7: =IF(B7="","",AB7/(1-Parâmetros!$B$7)) | AD7: =IF(B7="","",MAX(AA7*Parâmetros!$B$6,AC7)) | AE7: =IF(B7="","",(AD7-AB7)/AD7) | AF7: =IF(B7="","",AA7/Parâmetros!$B$10)
N8: =IF(B8="","",Parâmetros!$B$16*C8) | O8: =IF(B8="","",Parâmetros!$B$17*C8) | P8: =IF(B8="","",D8*Parâmetros!$B$18*C8) | Q8: =IF(B8="","",E8*Parâmetros!$B$19*C8) | R8: =IF(B8="","",F8*Parâmetros!$B$20*C8) | S8: =IF(B8="","",(G8*Parâmetros!$B$21+H8*Parâmetros!$B$22)*C8) | T8: =IF(B8="","",I8*Parâmetros!$B$23*C8) | U8: =IF(B8="","",J8*Parâmetros!$B$24*C8) | V8: =IF(B8="","",K8*Parâmetros!$B$25*C8) | W8: =IF(B8="","",L8*Parâmetros!$B$26*C8) | X8: =IF(B8="","",SUM(N8:W8)+M8) | Y8: =IF(B8="","",X8*Parâmetros!$B$8) | Z8: =IF(B8="","",X8*Parâmetros!$B$9) | AA8: =IF(B8="","",SUM(X8:Z8)) | AB8: =IF(B8="","",AA8*Parâmetros!$B$5) | AC8: =IF(B8="","",AB8/(1-Parâmetros!$B$7)) | AD8: =IF(B8="","",MAX(AA8*Parâmetros!$B$6,AC8)) | AE8: =IF(B8="","",(AD8-AB8)/AD8) | AF8: =IF(B8="","",AA8/Parâmetros!$B$10)
N9: =IF(B9="","",Parâmetros!$B$16*C9) | O9: =IF(B9="","",Parâmetros!$B$17*C9) | P9: =IF(B9="","",D9*Parâmetros!$B$18*C9) | Q9: =IF(B9="","",E9*Parâmetros!$B$19*C9) | R9: =IF(B9="","",F9*Parâmetros!$B$20*C9) | S9: =IF(B9="","",(G9*Parâmetros!$B$21+H9*Parâmetros!$B$22)*C9) | T9: =IF(B9="","",I9*Parâmetros!$B$23*C9) | U9: =IF(B9="","",J9*Parâmetros!$B$24*C9) | V9: =IF(B9="","",K9*Parâmetros!$B$25*C9) | W9: =IF(B9="","",L9*Parâmetros!$B$26*C9) | X9: =IF(B9="","",SUM(N9:W9)+M9) | Y9: =IF(B9="","",X9*Parâmetros!$B$8) | Z9: =IF(B9="","",X9*Parâmetros!$B$9) | AA9: =IF(B9="","",SUM(X9:Z9)) | AB9: =IF(B9="","",AA9*Parâmetros!$B$5) | AC9: =IF(B9="","",AB9/(1-Parâmetros!$B$7)) | AD9: =IF(B9="","",MAX(AA9*Parâmetros!$B$6,AC9)) | AE9: =IF(B9="","",(AD9-AB9)/AD9) | AF9: =IF(B9="","",AA9/Parâmetros!$B$10)
N10: =IF(B10="","",Parâmetros!$B$16*C10) | O10: =IF(B10="","",Parâmetros!$B$17*C10) | P10: =IF(B10="","",D10*Parâmetros!$B$18*C10) | Q10: =IF(B10="","",E10*Parâmetros!$B$19*C10) | R10: =IF(B10="","",F10*Parâmetros!$B$20*C10) | S10: =IF(B10="","",(G10*Parâmetros!$B$21+H10*Parâmetros!$B$22)*C10) | T10: =IF(B10="","",I10*Parâmetros!$B$23*C10) | U10: =IF(B10="","",J10*Parâmetros!$B$24*C10) | V10: =IF(B10="","",K10*Parâmetros!$B$25*C10) | W10: =IF(B10="","",L10*Parâmetros!$B$26*C10) | X10: =IF(B10="","",SUM(N10:W10)+M10) | Y10: =IF(B10="","",X10*Parâmetros!$B$8) | Z10: =IF(B10="","",X10*Parâmetros!$B$9) | AA10: =IF(B10="","",SUM(X10:Z10)) | AB10: =IF(B10="","",AA10*Parâmetros!$B$5) | AC10: =IF(B10="","",AB10/(1-Parâmetros!$B$7)) | AD10: =IF(B10="","",MAX(AA10*Parâmetros!$B$6,AC10)) | AE10: =IF(B10="","",(AD10-AB10)/AD10) | AF10: =IF(B10="","",AA10/Parâmetros!$B$10)
N11: =IF(B11="","",Parâmetros!$B$16*C11) | O11: =IF(B11="","",Parâmetros!$B$17*C11) | P11: =IF(B11="","",D11*Parâmetros!$B$18*C11) | Q11: =IF(B11="","",E11*Parâmetros!$B$19*C11) | R11: =IF(B11="","",F11*Parâmetros!$B$20*C11) | S11: =IF(B11="","",(G11*Parâmetros!$B$21+H11*Parâmetros!$B$22)*C11) | T11: =IF(B11="","",I11*Parâmetros!$B$23*C11) | U11: =IF(B11="","",J11*Parâmetros!$B$24*C11) | V11: =IF(B11="","",K11*Parâmetros!$B$25*C11) | W11: =IF(B11="","",L11*Parâmetros!$B$26*C11) | X11: =IF(B11="","",SUM(N11:W11)+M11) | Y11: =IF(B11="","",X11*Parâmetros!$B$8) | Z11: =IF(B11="","",X11*Parâmetros!$B$9) | AA11: =IF(B11="","",SUM(X11:Z11)) | AB11: =IF(B11="","",AA11*Parâmetros!$B$5) | AC11: =IF(B11="","",AB11/(1-Parâmetros!$B$7)) | AD11: =IF(B11="","",MAX(AA11*Parâmetros!$B$6,AC11)) | AE11: =IF(B11="","",(AD11-AB11)/AD11) | AF11: =IF(B11="","",AA11/Parâmetros!$B$10)
N12: =IF(B12="","",Parâmetros!$B$16*C12) | O12: =IF(B12="","",Parâmetros!$B$17*C12) | P12: =IF(B12="","",D12*Parâmetros!$B$18*C12) | Q12: =IF(B12="","",E12*Parâmetros!$B$19*C12) | R12: =IF(B12="","",F12*Parâmetros!$B$20*C12) | S12: =IF(B12="","",(G12*Parâmetros!$B$21+H12*Parâmetros!$B$22)*C12) | T12: =IF(B12="","",I12*Parâmetros!$B$23*C12) | U12: =IF(B12="","",J12*Parâmetros!$B$24*C12) | V12: =IF(B12="","",K12*Parâmetros!$B$25*C12) | W12: =IF(B12="","",L12*Parâmetros!$B$26*C12) | X12: =IF(B12="","",SUM(N12:W12)+M12) | Y12: =IF(B12="","",X12*Parâmetros!$B$8) | Z12: =IF(B12="","",X12*Parâmetros!$B$9) | AA12: =IF(B12="","",SUM(X12:Z12)) | AB12: =IF(B12="","",AA12*Parâmetros!$B$5) | AC12: =IF(B12="","",AB12/(1-Parâmetros!$B$7)) | AD12: =IF(B12="","",MAX(AA12*Parâmetros!$B$6,AC12)) | AE12: =IF(B12="","",(AD12-AB12)/AD12) | AF12: =IF(B12="","",AA12/Parâmetros!$B$10)
N13: =IF(B13="","",Parâmetros!$B$16*C13) | O13: =IF(B13="","",Parâmetros!$B$17*C13) | P13: =IF(B13="","",D13*Parâmetros!$B$18*C13) | Q13: =IF(B13="","",E13*Parâmetros!$B$19*C13) | R13: =IF(B13="","",F13*Parâmetros!$B$20*C13) | S13: =IF(B13="","",(G13*Parâmetros!$B$21+H13*Parâmetros!$B$22)*C13) | T13: =IF(B13="","",I13*Parâmetros!$B$23*C13) | U13: =IF(B13="","",J13*Parâmetros!$B$24*C13) | V13: =IF(B13="","",K13*Parâmetros!$B$25*C13) | W13: =IF(B13="","",L13*Parâmetros!$B$26*C13) | X13: =IF(B13="","",SUM(N13:W13)+M13) | Y13: =IF(B13="","",X13*Parâmetros!$B$8) | Z13: =IF(B13="","",X13*Parâmetros!$B$9) | AA13: =IF(B13="","",SUM(X13:Z13)) | AB13: =IF(B13="","",AA13*Parâmetros!$B$5) | AC13: =IF(B13="","",AB13/(1-Parâmetros!$B$7)) | AD13: =IF(B13="","",MAX(AA13*Parâmetros!$B$6,AC13)) | AE13: =IF(B13="","",(AD13-AB13)/AD13) | AF13: =IF(B13="","",AA13/Parâmetros!$B$10)
N14: =IF(B14="","",Parâmetros!$B$16*C14) | O14: =IF(B14="","",Parâmetros!$B$17*C14) | P14: =IF(B14="","",D14*Parâmetros!$B$18*C14) | Q14: =IF(B14="","",E14*Parâmetros!$B$19*C14) | R14: =IF(B14="","",F14*Parâmetros!$B$20*C14) | S14: =IF(B14="","",(G14*Parâmetros!$B$21+H14*Parâmetros!$B$22)*C14) | T14: =IF(B14="","",I14*Parâmetros!$B$23*C14) | U14: =IF(B14="","",J14*Parâmetros!$B$24*C14) | V14: =IF(B14="","",K14*Parâmetros!$B$25*C14) | W14: =IF(B14="","",L14*Parâmetros!$B$26*C14) | X14: =IF(B14="","",SUM(N14:W14)+M14) | Y14: =IF(B14="","",X14*Parâmetros!$B$8) | Z14: =IF(B14="","",X14*Parâmetros!$B$9) | AA14: =IF(B14="","",SUM(X14:Z14)) | AB14: =IF(B14="","",AA14*Parâmetros!$B$5) | AC14: =IF(B14="","",AB14/(1-Parâmetros!$B$7)) | AD14: =IF(B14="","",MAX(AA14*Parâmetros!$B$6,AC14)) | AE14: =IF(B14="","",(AD14-AB14)/AD14) | AF14: =IF(B14="","",AA14/Parâmetros!$B$10)
N15: =IF(B15="","",Parâmetros!$B$16*C15) | O15: =IF(B15="","",Parâmetros!$B$17*C15) | P15: =IF(B15="","",D15*Parâmetros!$B$18*C15) | Q15: =IF(B15="","",E15*Parâmetros!$B$19*C15) | R15: =IF(B15="","",F15*Parâmetros!$B$20*C15) | S15: =IF(B15="","",(G15*Parâmetros!$B$21+H15*Parâmetros!$B$22)*C15) | T15: =IF(B15="","",I15*Parâmetros!$B$23*C15) | U15: =IF(B15="","",J15*Parâmetros!$B$24*C15) | V15: =IF(B15="","",K15*Parâmetros!$B$25*C15) | W15: =IF(B15="","",L15*Parâmetros!$B$26*C15) | X15: =IF(B15="","",SUM(N15:W15)+M15) | Y15: =IF(B15="","",X15*Parâmetros!$B$8) | Z15: =IF(B15="","",X15*Parâmetros!$B$9) | AA15: =IF(B15="","",SUM(X15:Z15)) | AB15: =IF(B15="","",AA15*Parâmetros!$B$5) | AC15: =IF(B15="","",AB15/(1-Parâmetros!$B$7)) | AD15: =IF(B15="","",MAX(AA15*Parâmetros!$B$6,AC15)) | AE15: =IF(B15="","",(AD15-AB15)/AD15) | AF15: =IF(B15="","",AA15/Parâmetros!$B$10)
N16: =IF(B16="","",Parâmetros!$B$16*C16) | O16: =IF(B16="","",Parâmetros!$B$17*C16) | P16: =IF(B16="","",D16*Parâmetros!$B$18*C16) | Q16: =IF(B16="","",E16*Parâmetros!$B$19*C16) | R16: =IF(B16="","",F16*Parâmetros!$B$20*C16) | S16: =IF(B16="","",(G16*Parâmetros!$B$21+H16*Parâmetros!$B$22)*C16) | T16: =IF(B16="","",I16*Parâmetros!$B$23*C16) | U16: =IF(B16="","",J16*Parâmetros!$B$24*C16) | V16: =IF(B16="","",K16*Parâmetros!$B$25*C16) | W16: =IF(B16="","",L16*Parâmetros!$B$26*C16) | X16: =IF(B16="","",SUM(N16:W16)+M16) | Y16: =IF(B16="","",X16*Parâmetros!$B$8) | Z16: =IF(B16="","",X16*Parâmetros!$B$9) | AA16: =IF(B16="","",SUM(X16:Z16)) | AB16: =IF(B16="","",AA16*Parâmetros!$B$5) | AC16: =IF(B16="","",AB16/(1-Parâmetros!$B$7)) | AD16: =IF(B16="","",MAX(AA16*Parâmetros!$B$6,AC16)) | AE16: =IF(B16="","",(AD16-AB16)/AD16) | AF16: =IF(B16="","",AA16/Parâmetros!$B$10)
N17: =IF(B17="","",Parâmetros!$B$16*C17) | O17: =IF(B17="","",Parâmetros!$B$17*C17) | P17: =IF(B17="","",D17*Parâmetros!$B$18*C17) | Q17: =IF(B17="","",E17*Parâmetros!$B$19*C17) | R17: =IF(B17="","",F17*Parâmetros!$B$20*C17) | S17: =IF(B17="","",(G17*Parâmetros!$B$21+H17*Parâmetros!$B$22)*C17) | T17: =IF(B17="","",I17*Parâmetros!$B$23*C17) | U17: =IF(B17="","",J17*Parâmetros!$B$24*C17) | V17: =IF(B17="","",K17*Parâmetros!$B$25*C17) | W17: =IF(B17="","",L17*Parâmetros!$B$26*C17) | X17: =IF(B17="","",SUM(N17:W17)+M17) | Y17: =IF(B17="","",X17*Parâmetros!$B$8) | Z17: =IF(B17="","",X17*Parâmetros!$B$9) | AA17: =IF(B17="","",SUM(X17:Z17)) | AB17: =IF(B17="","",AA17*Parâmetros!$B$5) | AC17: =IF(B17="","",AB17/(1-Parâmetros!$B$7)) | AD17: =IF(B17="","",MAX(AA17*Parâmetros!$B$6,AC17)) | AE17: =IF(B17="","",(AD17-AB17)/AD17) | AF17: =IF(B17="","",AA17/Parâmetros!$B$10)
... N54: =IF(B54="","",Parâmetros!$B$16*C54) | O54: =IF(B54="","",Parâmetros!$B$17*C54) | P54: =IF(B54="","",D54*Parâmetros!$B$18*C54) | Q54: =IF(B54="","",E54*Parâmetros!$B$19*C54) | R54: =IF(B54="","",F54*Parâmetros!$B$20*C54) | S54: =IF(B54="","",(G54*Parâmetros!$B$21+H54*Parâmetros!$B$22)*C54) | T54: =IF(B54="","",I54*Parâmetros!$B$23*C54) | U54: =IF(B54="","",J54*Parâmetros!$B$24*C54) | V54: =IF(B54="","",K54*Parâmetros!$B$25*C54) | W54: =IF(B54="","",L54*Parâmetros!$B$26*C54) | X54: =IF(B54="","",SUM(N54:W54)+M54) | Y54: =IF(B54="","",X54*Parâmetros!$B$8) | Z54: =IF(B54="","",X54*Parâmetros!$B$9) | AA54: =IF(B54="","",SUM(X54:Z54)) | AB54: =IF(B54="","",AA54*Parâmetros!$B$5) | AC54: =IF(B54="","",AB54/(1-Parâmetros!$B$7)) | AD54: =IF(B54="","",MAX(AA54*Parâmetros!$B$6,AC54)) | AE54: =IF(B54="","",(AD54-AB54)/AD54) | AF54: =IF(B54="","",AA54/Parâmetros!$B$10)

Sheet Onboarding
A1: Briefing de onboarding
A2: Use após o fechamento. A coluna Evidência esperada evita respostas vagas.
A4: Bloco | B4: Pergunta | C4: Evidência esperada | D4: Obrigatoriedade | E4: Resposta/Link | F4: Responsável | G4: Prazo | H4: Status
A5: Objetivo | B5: Quais dores foram contratadas e em que ordem serão atacadas? | C5: Lista priorizada | D5: Obrigatório
A6: Objetivo | B6: Qual resultado deve ser alcançado em 30, 60 e 90 dias? | C6: Meta e prazo | D6: Obrigatório
A7: Baseline | B7: Qual é a linha de base de volume, tempo, conversão, custo e qualidade? | C7: Relatório ou amostra | D7: Obrigatório
A8: Processo | B8: Qual é o fluxo completo, incluindo exceções e caminhos alternativos? | C8: Fluxograma validado | D8: Obrigatório
A9: Agentes | B9: Quantos papéis distintos exigem contexto, permissões ou métricas diferentes? | C9: Lista de agentes | D9: Obrigatório
A10: Fluxos | B10: Quais são as principais intenções e o resultado esperado de cada uma? | C10: Matriz intenção x ação | D10: Obrigatório
A11: Qualificação | B11: Quais critérios qualificam, desqualificam ou priorizam um contato? | C11: Regras objetivas | D11: Se aplicável
A12: Regras | B12: Quais regras nunca podem ser quebradas e quem autoriza exceções? | C12: Política validada | D12: Obrigatório
A13: Limites | B13: O que a IA não pode dizer, decidir, consultar ou alterar? | C13: Lista de proibições | D13: Obrigatório
A14: Handoff | B14: Quando, para quem e com qual resumo a IA transfere? | C14: Matriz de escalonamento | D14: Obrigatório
A15: Integrações | B15: O que cada sistema permite consultar, criar ou atualizar? | C15: Acesso e documentação | D15: Se aplicável
A16: Conhecimento | B16: Quais fontes são oficiais e qual hierarquia resolve conflitos? | C16: Fontes e proprietário | D16: Obrigatório
... A22: Governança | B22: Quem responde por conteúdo, operação, técnica e decisão? | C22: RACI | D22: Obrigatório

Sheet Plano do Cliente
A1: Plano de Onboarding por agente
A2: Uma linha por agente. Esta aba transforma o briefing em especificação executável.
A4: Cliente | B4: Agente | C4: Papel | D4: Canal | E4: Gatilho inicial | F4: Responsabilidades | G4: Fora de escopo | H4: Dados de entrada | I4: Saídas | J4: Regras de decisão | K4: Handoff humano | L4: Integrações | M4: Fonte oficial | N4: Dono Avraham | O4: Dono cliente | P4: Métrica principal | Q4: Baseline | R4: Meta 90 dias | S4: Critério de aceite | T4: Go-live | U4: Status
A5: Cliente Exemplo | B5: Agente SDR | C5: Qualificar e encaminhar | D5: WhatsApp | E5: Resposta à prospecção | F5: Responder, qualificar, registrar e agendar | G5: Negociar desconto | H5: Nome, empresa, necessidade | I5: Lead qualificado + resumo | J5: Priorizar fit alto | K5: Transferir exceções | L5: CRM + Agenda | M5: Tabela comercial | N5: Líder IA | O5: Gerente comercial | P5: Leads qualificados | Q5: 120 | R5: 180 | S5: 10 cenários aprovados | T5: 01/11/2026 | U5: Planejado

Sheet Operação Mensal
A1: Custos e mensalidade
A2: Estime consumo e operação por cliente/mês. Preços de modelo e câmbio vêm da aba Parâmetros.
A4: Cliente | B4: Mês | C4: Agentes ativos | D4: Conversas | E4: Turnos/conversa | F4: Tokens entrada/turno | G4: Tokens saída/turno | H4: Monitoramento (h) | I4: Otimização (h) | J4: Suporte (h) | K4: Relatório (h) | L4: Gestão cliente (h) | M4: Outras horas | N4: Total horas | O4: Custo trabalho | P4: Entrada (M tokens) | Q4: Saída (M tokens) | R4: Custo tokens | S4: Canal/infra/terceiros | T4: Custo mensal total | U4: Mensalidade mínima | V4: Impacto conservador | W4: Referência por valor | X4: Mensalidade sugerida | Y4: Mensalidade fechada | Z4: Margem prevista
A5: Cliente Exemplo | B5: nov/2026 | C5: 1 | D5: 1200 | E5: 8 | F5: 700 | G5: 180 | H5: 2 | I5: 4 | J5: 4 | K5: 3 | L5: 2 | M5: 0 | N5: =SUM(H5:M5) -> 15 | O5: =N5*Parâmetros!$B$5 -> 1800 | P5: =D5*E5*F5/1000000 -> 6.72 | Q5: =D5*E5*G5/1000000 -> 1.728 | R5: =(P5*Parâmetros!$B$14+Q5*Parâmetros!$B$15)*Parâmetros!$B$13*(1+Parâmetros!$B$12) -> 97.4688 | S5: 900 | T5: =O5+R5+S5 -> 2797.4688 | U5: =T5/(1-Parâmetros!$B$7) -> 6993.672 | V5: 25000 | W5: =V5*Parâmetros!$B$11 -> 2500 | X5: =MAX(U5,W5) -> 6993.672 | Y5: 6500 | Z5: =(Y5-T5)/Y5 -> 0.56962018
N6: =IF(A6="","",SUM(H6:M6)) | O6: =IF(A6="","",N6*Parâmetros!$B$5) | P6: =IF(A6="","",D6*E6*F6/1000000) | Q6: =IF(A6="","",D6*E6*G6/1000000) | R6: =IF(A6="","",(P6*Parâmetros!$B$14+Q6*Parâmetros!$B$15)*Parâmetros!$B$13*(1+Parâmetros!$B$12)) | T6: =IF(A6="","",O6+R6+S6) | U6: =IF(A6="","",T6/(1-Parâmetros!$B$7)) | W6: =IF(A6="","",V6*Parâmetros!$B$11) | X6: =IF(A6="","",MAX(U6,W6)) | Z6: =IF(A6="","",(Y6-T6)/Y6)
N7: =IF(A7="","",SUM(H7:M7)) | O7: =IF(A7="","",N7*Parâmetros!$B$5) | P7: =IF(A7="","",D7*E7*F7/1000000) | Q7: =IF(A7="","",D7*E7*G7/1000000) | R7: =IF(A7="","",(P7*Parâmetros!$B$14+Q7*Parâmetros!$B$15)*Parâmetros!$B$13*(1+Parâmetros!$B$12)) | T7: =IF(A7="","",O7+R7+S7) | U7: =IF(A7="","",T7/(1-Parâmetros!$B$7)) | W7: =IF(A7="","",V7*Parâmetros!$B$11) | X7: =IF(A7="","",MAX(U7,W7)) | Z7: =IF(A7="","",(Y7-T7)/Y7)
N8: =IF(A8="","",SUM(H8:M8)) | O8: =IF(A8="","",N8*Parâmetros!$B$5) | P8: =IF(A8="","",D8*E8*F8/1000000) | Q8: =IF(A8="","",D8*E8*G8/1000000) | R8: =IF(A8="","",(P8*Parâmetros!$B$14+Q8*Parâmetros!$B$15)*Parâmetros!$B$13*(1+Parâmetros!$B$12)) | T8: =IF(A8="","",O8+R8+S8) | U8: =IF(A8="","",T8/(1-Parâmetros!$B$7)) | W8: =IF(A8="","",V8*Parâmetros!$B$11) | X8: =IF(A8="","",MAX(U8,W8)) | Z8: =IF(A8="","",(Y8-T8)/Y8)
N9: =IF(A9="","",SUM(H9:M9)) | O9: =IF(A9="","",N9*Parâmetros!$B$5) | P9: =IF(A9="","",D9*E9*F9/1000000) | Q9: =IF(A9="","",D9*E9*G9/1000000) | R9: =IF(A9="","",(P9*Parâmetros!$B$14+Q9*Parâmetros!$B$15)*Parâmetros!$B$13*(1+Parâmetros!$B$12)) | T9: =IF(A9="","",O9+R9+S9) | U9: =IF(A9="","",T9/(1-Parâmetros!$B$7)) | W9: =IF(A9="","",V9*Parâmetros!$B$11) | X9: =IF(A9="","",MAX(U9,W9)) | Z9: =IF(A9="","",(Y9-T9)/Y9)
N10: =IF(A10="","",SUM(H10:M10)) | O10: =IF(A10="","",N10*Parâmetros!$B$5) | P10: =IF(A10="","",D10*E10*F10/1000000) | Q10: =IF(A10="","",D10*E10*G10/1000000) | R10: =IF(A10="","",(P10*Parâmetros!$B$14+Q10*Parâmetros!$B$15)*Parâmetros!$B$13*(1+Parâmetros!$B$12)) | T10: =IF(A10="","",O10+R10+S10) | U10: =IF(A10="","",T10/(1-Parâmetros!$B$7)) | W10: =IF(A10="","",V10*Parâmetros!$B$11) | X10: =IF(A10="","",MAX(U10,W10)) | Z10: =IF(A10="","",(Y10-T10)/Y10)
N11: =IF(A11="","",SUM(H11:M11)) | O11: =IF(A11="","",N11*Parâmetros!$B$5) | P11: =IF(A11="","",D11*E11*F11/1000000) | Q11: =IF(A11="","",D11*E11*G11/1000000) | R11: =IF(A11="","",(P11*Parâmetros!$B$14+Q11*Parâmetros!$B$15)*Parâmetros!$B$13*(1+Parâmetros!$B$12)) | T11: =IF(A11="","",O11+R11+S11) | U11: =IF(A11="","",T11/(1-Parâmetros!$B$7)) | W11: =IF(A11="","",V11*Parâmetros!$B$11) | X11: =IF(A11="","",MAX(U11,W11)) | Z11: =IF(A11="","",(Y11-T11)/Y11)
N12: =IF(A12="","",SUM(H12:M12)) | O12: =IF(A12="","",N12*Parâmetros!$B$5) | P12: =IF(A12="","",D12*E12*F12/1000000) | Q12: =IF(A12="","",D12*E12*G12/1000000) | R12: =IF(A12="","",(P12*Parâmetros!$B$14+Q12*Parâmetros!$B$15)*Parâmetros!$B$13*(1+Parâmetros!$B$12)) | T12: =IF(A12="","",O12+R12+S12) | U12: =IF(A12="","",T12/(1-Parâmetros!$B$7)) | W12: =IF(A12="","",V12*Parâmetros!$B$11) | X12: =IF(A12="","",MAX(U12,W12)) | Z12: =IF(A12="","",(Y12-T12)/Y12)
N13: =IF(A13="","",SUM(H13:M13)) | O13: =IF(A13="","",N13*Parâmetros!$B$5) | P13: =IF(A13="","",D13*E13*F13/1000000) | Q13: =IF(A13="","",D13*E13*G13/1000000) | R13: =IF(A13="","",(P13*Parâmetros!$B$14+Q13*Parâmetros!$B$15)*Parâmetros!$B$13*(1+Parâmetros!$B$12)) | T13: =IF(A13="","",O13+R13+S13) | U13: =IF(A13="","",T13/(1-Parâmetros!$B$7)) | W13: =IF(A13="","",V13*Parâmetros!$B$11) | X13: =IF(A13="","",MAX(U13,W13)) | Z13: =IF(A13="","",(Y13-T13)/Y13)
N14: =IF(A14="","",SUM(H14:M14)) | O14: =IF(A14="","",N14*Parâmetros!$B$5) | P14: =IF(A14="","",D14*E14*F14/1000000) | Q14: =IF(A14="","",D14*E14*G14/1000000) | R14: =IF(A14="","",(P14*Parâmetros!$B$14+Q14*Parâmetros!$B$15)*Parâmetros!$B$13*(1+Parâmetros!$B$12)) | T14: =IF(A14="","",O14+R14+S14) | U14: =IF(A14="","",T14/(1-Parâmetros!$B$7)) | W14: =IF(A14="","",V14*Parâmetros!$B$11) | X14: =IF(A14="","",MAX(U14,W14)) | Z14: =IF(A14="","",(Y14-T14)/Y14)
N15: =IF(A15="","",SUM(H15:M15)) | O15: =IF(A15="","",N15*Parâmetros!$B$5) | P15: =IF(A15="","",D15*E15*F15/1000000) | Q15: =IF(A15="","",D15*E15*G15/1000000) | R15: =IF(A15="","",(P15*Parâmetros!$B$14+Q15*Parâmetros!$B$15)*Parâmetros!$B$13*(1+Parâmetros!$B$12)) | T15: =IF(A15="","",O15+R15+S15) | U15: =IF(A15="","",T15/(1-Parâmetros!$B$7)) | W15: =IF(A15="","",V15*Parâmetros!$B$11) | X15: =IF(A15="","",MAX(U15,W15)) | Z15: =IF(A15="","",(Y15-T15)/Y15)
N16: =IF(A16="","",SUM(H16:M16)) | O16: =IF(A16="","",N16*Parâmetros!$B$5) | P16: =IF(A16="","",D16*E16*F16/1000000) | Q16: =IF(A16="","",D16*E16*G16/1000000) | R16: =IF(A16="","",(P16*Parâmetros!$B$14+Q16*Parâmetros!$B$15)*Parâmetros!$B$13*(1+Parâmetros!$B$12)) | T16: =IF(A16="","",O16+R16+S16) | U16: =IF(A16="","",T16/(1-Parâmetros!$B$7)) | W16: =IF(A16="","",V16*Parâmetros!$B$11) | X16: =IF(A16="","",MAX(U16,W16)) | Z16: =IF(A16="","",(Y16-T16)/Y16)
N17: =IF(A17="","",SUM(H17:M17)) | O17: =IF(A17="","",N17*Parâmetros!$B$5) | P17: =IF(A17="","",D17*E17*F17/1000000) | Q17: =IF(A17="","",D17*E17*G17/1000000) | R17: =IF(A17="","",(P17*Parâmetros!$B$14+Q17*Parâmetros!$B$15)*Parâmetros!$B$13*(1+Parâmetros!$B$12)) | T17: =IF(A17="","",O17+R17+S17) | U17: =IF(A17="","",T17/(1-Parâmetros!$B$7)) | W17: =IF(A17="","",V17*Parâmetros!$B$11) | X17: =IF(A17="","",MAX(U17,W17)) | Z17: =IF(A17="","",(Y17-T17)/Y17)
... N54: =IF(A54="","",SUM(H54:M54)) | O54: =IF(A54="","",N54*Parâmetros!$B$5) | P54: =IF(A54="","",D54*E54*F54/1000000) | Q54: =IF(A54="","",D54*E54*G54/1000000) | R54: =IF(A54="","",(P54*Parâmetros!$B$14+Q54*Parâmetros!$B$15)*Parâmetros!$B$13*(1+Parâmetros!$B$12)) | T54: =IF(A54="","",O54+R54+S54) | U54: =IF(A54="","",T54/(1-Parâmetros!$B$7)) | W54: =IF(A54="","",V54*Parâmetros!$B$11) | X54: =IF(A54="","",MAX(U54,W54)) | Z54: =IF(A54="","",(Y54-T54)/Y54)

Sheet Relatório ROI
A1: Relatório mensal de impacto e ROI
A2: Compare períodos equivalentes. Separe valores observados de estimativas e não conte o mesmo impacto duas vezes.
A4: Cliente | B4: Mês | C4: Leads baseline | D4: Leads atual | E4: Resposta baseline (min) | F4: Resposta atual (min) | G4: Conversão baseline | H4: Conversão atual | I4: Vendas incrementais | J4: Ticket médio | K4: Margem contribuição | L4: Margem incremental | M4: Horas humanas baseline | N4: Horas humanas atual | O4: Horas liberadas | P4: Custo humano/h | Q4: Economia trabalho | R4: Perdas evitadas | S4: Impacto total | T4: Setup pago | U4: Mensalidade | V4: Outros custos cliente | W4: Investimento do mês | X4: Benefício líquido | Y4: ROI mensal | Z4: Payback setup (meses) | AA4: Tipo de evidência | AB4: Fonte/observação
A5: Cliente Exemplo | B5: nov/2026 | C5: 1200 | D5: 1250 | E5: 180 | F5: 4 | G5: 0.08 | H5: 0.1 | I5: =MAX(0,D5*H5-C5*G5) -> 29 | J5: 2500 | K5: 0.35 | L5: =I5*J5*K5 -> 25375 | M5: 180 | N5: 120 | O5: =MAX(0,M5-N5) -> 60 | P5: 55 | Q5: =O5*P5 -> 3300 | R5: 1000 | S5: =L5+Q5+R5 -> 29675 | T5: 12000 | U5: 6500 | V5: 0 | W5: =U5+V5 -> 6500 | X5: =S5-W5 -> 23175 | Y5: =IF(W5=0,0,X5/W5) -> 3.5653846 | Z5: =IF(X5<=0,0,T5/X5) -> 0.51779935 | AA5: Observado | AB5: CRM + folha de ponto
I6: =IF(A6="","",MAX(0,D6*H6-C6*G6)) | L6: =IF(A6="","",I6*J6*K6) | O6: =IF(A6="","",MAX(0,M6-N6)) | Q6: =IF(A6="","",O6*P6) | S6: =IF(A6="","",L6+Q6+R6) | W6: =IF(A6="","",U6+V6) | X6: =IF(A6="","",S6-W6) | Y6: =IF(A6="","",IF(W6=0,0,X6/W6)) | Z6: =IF(A6="","",IF(X6<=0,0,T6/X6))
I7: =IF(A7="","",MAX(0,D7*H7-C7*G7)) | L7: =IF(A7="","",I7*J7*K7) | O7: =IF(A7="","",MAX(0,M7-N7)) | Q7: =IF(A7="","",O7*P7) | S7: =IF(A7="","",L7+Q7+R7) | W7: =IF(A7="","",U7+V7) | X7: =IF(A7="","",S7-W7) | Y7: =IF(A7="","",IF(W7=0,0,X7/W7)) | Z7: =IF(A7="","",IF(X7<=0,0,T7/X7))
I8: =IF(A8="","",MAX(0,D8*H8-C8*G8)) | L8: =IF(A8="","",I8*J8*K8) | O8: =IF(A8="","",MAX(0,M8-N8)) | Q8: =IF(A8="","",O8*P8) | S8: =IF(A8="","",L8+Q8+R8) | W8: =IF(A8="","",U8+V8) | X8: =IF(A8="","",S8-W8) | Y8: =IF(A8="","",IF(W8=0,0,X8/W8)) | Z8: =IF(A8="","",IF(X8<=0,0,T8/X8))
I9: =IF(A9="","",MAX(0,D9*H9-C9*G9)) | L9: =IF(A9="","",I9*J9*K9) | O9: =IF(A9="","",MAX(0,M9-N9)) | Q9: =IF(A9="","",O9*P9) | S9: =IF(A9="","",L9+Q9+R9) | W9: =IF(A9="","",U9+V9) | X9: =IF(A9="","",S9-W9) | Y9: =IF(A9="","",IF(W9=0,0,X9/W9)) | Z9: =IF(A9="","",IF(X9<=0,0,T9/X9))
I10: =IF(A10="","",MAX(0,D10*H10-C10*G10)) | L10: =IF(A10="","",I10*J10*K10) | O10: =IF(A10="","",MAX(0,M10-N10)) | Q10: =IF(A10="","",O10*P10) | S10: =IF(A10="","",L10+Q10+R10) | W10: =IF(A10="","",U10+V10) | X10: =IF(A10="","",S10-W10) | Y10: =IF(A10="","",IF(W10=0,0,X10/W10)) | Z10: =IF(A10="","",IF(X10<=0,0,T10/X10))
I11: =IF(A11="","",MAX(0,D11*H11-C11*G11)) | L11: =IF(A11="","",I11*J11*K11) | O11: =IF(A11="","",MAX(0,M11-N11)) | Q11: =IF(A11="","",O11*P11) | S11: =IF(A11="","",L11+Q11+R11) | W11: =IF(A11="","",U11+V11) | X11: =IF(A11="","",S11-W11) | Y11: =IF(A11="","",IF(W11=0,0,X11/W11)) | Z11: =IF(A11="","",IF(X11<=0,0,T11/X11))
I12: =IF(A12="","",MAX(0,D12*H12-C12*G12)) | L12: =IF(A12="","",I12*J12*K12) | O12: =IF(A12="","",MAX(0,M12-N12)) | Q12: =IF(A12="","",O12*P12) | S12: =IF(A12="","",L12+Q12+R12) | W12: =IF(A12="","",U12+V12) | X12: =IF(A12="","",S12-W12) | Y12: =IF(A12="","",IF(W12=0,0,X12/W12)) | Z12: =IF(A12="","",IF(X12<=0,0,T12/X12))
I13: =IF(A13="","",MAX(0,D13*H13-C13*G13)) | L13: =IF(A13="","",I13*J13*K13) | O13: =IF(A13="","",MAX(0,M13-N13)) | Q13: =IF(A13="","",O13*P13) | S13: =IF(A13="","",L13+Q13+R13) | W13: =IF(A13="","",U13+V13) | X13: =IF(A13="","",S13-W13) | Y13: =IF(A13="","",IF(W13=0,0,X13/W13)) | Z13: =IF(A13="","",IF(X13<=0,0,T13/X13))
I14: =IF(A14="","",MAX(0,D14*H14-C14*G14)) | L14: =IF(A14="","",I14*J14*K14) | O14: =IF(A14="","",MAX(0,M14-N14)) | Q14: =IF(A14="","",O14*P14) | S14: =IF(A14="","",L14+Q14+R14) | W14: =IF(A14="","",U14+V14) | X14: =IF(A14="","",S14-W14) | Y14: =IF(A14="","",IF(W14=0,0,X14/W14)) | Z14: =IF(A14="","",IF(X14<=0,0,T14/X14))
I15: =IF(A15="","",MAX(0,D15*H15-C15*G15)) | L15: =IF(A15="","",I15*J15*K15) | O15: =IF(A15="","",MAX(0,M15-N15)) | Q15: =IF(A15="","",O15*P15) | S15: =IF(A15="","",L15+Q15+R15) | W15: =IF(A15="","",U15+V15) | X15: =IF(A15="","",S15-W15) | Y15: =IF(A15="","",IF(W15=0,0,X15/W15)) | Z15: =IF(A15="","",IF(X15<=0,0,T15/X15))
I16: =IF(A16="","",MAX(0,D16*H16-C16*G16)) | L16: =IF(A16="","",I16*J16*K16) | O16: =IF(A16="","",MAX(0,M16-N16)) | Q16: =IF(A16="","",O16*P16) | S16: =IF(A16="","",L16+Q16+R16) | W16: =IF(A16="","",U16+V16) | X16: =IF(A16="","",S16-W16) | Y16: =IF(A16="","",IF(W16=0,0,X16/W16)) | Z16: =IF(A16="","",IF(X16<=0,0,T16/X16))
I17: =IF(A17="","",MAX(0,D17*H17-C17*G17)) | L17: =IF(A17="","",I17*J17*K17) | O17: =IF(A17="","",MAX(0,M17-N17)) | Q17: =IF(A17="","",O17*P17) | S17: =IF(A17="","",L17+Q17+R17) | W17: =IF(A17="","",U17+V17) | X17: =IF(A17="","",S17-W17) | Y17: =IF(A17="","",IF(W17=0,0,X17/W17)) | Z17: =IF(A17="","",IF(X17<=0,0,T17/X17))
... I54: =IF(A54="","",MAX(0,D54*H54-C54*G54)) | L54: =IF(A54="","",I54*J54*K54) | O54: =IF(A54="","",MAX(0,M54-N54)) | Q54: =IF(A54="","",O54*P54) | S54: =IF(A54="","",L54+Q54+R54) | W54: =IF(A54="","",U54+V54) | X54: =IF(A54="","",S54-W54) | Y54: =IF(A54="","",IF(W54=0,0,X54/W54)) | Z54: =IF(A54="","",IF(X54<=0,0,T54/X54))
